README.md
setup.py
lens_csv/__init__.py
lens_csv.egg-info/PKG-INFO
lens_csv.egg-info/SOURCES.txt
lens_csv.egg-info/dependency_links.txt
lens_csv.egg-info/requires.txt
lens_csv.egg-info/top_level.txt