Metadata-Version: 2.1
Name: lens-csv
Version: 0.0.3
Summary: A CSV parser for lens
Home-page: https://github.com/port-zero/lens_csv
Author: Veit Heller
License: MIT
Download-URL: https://github.com/port-zero/lens_csv/tarball/0.0.3
Platform: UNKNOWN
